bot_base/__init__.py
bot_base/bot.py
bot_base/cancellable_wait_for.py
bot_base/cog.py
bot_base/context.py
bot_base/exceptions.py
bot_base/blacklist/__init__.py
bot_base/blacklist/blacklist.py
bot_base/caches/__init__.py
bot_base/caches/abc.py
bot_base/caches/entry.py
bot_base/caches/timed.py
bot_base/cogs/__init__.py
bot_base/cogs/internal.py
bot_base/converters/__init__.py
bot_base/converters/time.py
bot_base/db/__init__.py
bot_base/db/mongo.py
bot_base/paginators/__init__.py
bot_base/paginators/disnake_paginator.py
bot_base/wraps/__init__.py
bot_base/wraps/channel.py
bot_base/wraps/member.py
bot_base/wraps/meta.py
bot_base/wraps/thread.py
bot_base/wraps/user.py
Bot_Base-1.7.1.dist-info/LICENSE
Bot_Base-1.7.1.dist-info/METADATA
Bot_Base-1.7.1.dist-info/WHEEL
Bot_Base-1.7.1.dist-info/top_level.txt
Bot_Base-1.7.1.dist-info/RECORD
