Metadata-Version: 2.1
Name: Bot-Base
Version: 1.7.1
Summary: A simplistic yet feature rich discord bot template.
Home-page: https://github.com/Skelmis/DPY-Bot-Base
Author: Skelmis
Author-email: ethan@koldfusion.xyz
License: UNKNOWN
Platform: UNKNOWN
Classifier: Programming Language :: Python :: 3
Classifier: Operating System :: OS Independent
Classifier: Development Status :: 5 - Production/Stable
Requires-Python: >=3.8
License-File: LICENSE
Requires-Dist: dnspython (==2.2.1)
Requires-Dist: motor (==3.0.0)
Requires-Dist: humanize (==4.2.0)
Requires-Dist: attrs (>=21.4.0)
Requires-Dist: alaric (>=1.0.1)
